justserver/__init__.py
justserver/cli.py
justserver/daemon/__init__.py
justserver/daemon/api.py
justserver/daemon/ip_mapper.py
justserver/daemon/justniffer_ext.py
justserver/daemon/settings.py
justserver/logging.py
justserver/model.py
justserver/proxy/__init__.py
justserver/proxy/endpoints.py
justserver/proxy/proxy.py
justserver/proxy/settings.py
justserver/settings_log.py
justserver-0.1.46.dist-info/METADATA
justserver-0.1.46.dist-info/WHEEL
justserver-0.1.46.dist-info/entry_points.txt
justserver-0.1.46.dist-info/RECORD
