Metadata-Version: 2.3
Name: justserver
Version: 0.1.46
Summary: 
Author: Knspar
Author-email: knspar@proton.me
Requires-Python: >=3.12,<4.0
Classifier: Programming Language :: Python :: 3
Classifier: Programming Language :: Python :: 3.12
Classifier: Programming Language :: Python :: 3.13
Requires-Dist: dynaconf (>=3.2.10,<4.0.0)
Requires-Dist: fastapi (>=0.115.12,<0.116.0)
Requires-Dist: httpx (>=0.28.1,<0.29.0)
Requires-Dist: ipython (>=9.1.0,<10.0.0)
Requires-Dist: justniffer-cli (>=0.2.2,<0.3.0)
Requires-Dist: kubernetes (>=32.0.1,<33.0.0)
Requires-Dist: loguru (>=0.7.3,<0.8.0)
Requires-Dist: pudb (>=2024.1.3,<2025.0.0)
Requires-Dist: pydantic (>=2.11.2,<3.0.0)
Requires-Dist: typer (>=0.15.2,<0.16.0)
Requires-Dist: uvicorn (>=0.34.0,<0.35.0)
